letta_mcp/__init__.py
letta_mcp/_version.py
letta_mcp/cli.py
letta_mcp/config.py
letta_mcp/exceptions.py
letta_mcp/models.py
letta_mcp/server.py
letta_mcp/utils.py
letta_mcp_server-1.0.5.dist-info/licenses/LICENSE
letta_mcp_server-1.0.5.dist-info/METADATA
letta_mcp_server-1.0.5.dist-info/WHEEL
letta_mcp_server-1.0.5.dist-info/entry_points.txt
letta_mcp_server-1.0.5.dist-info/top_level.txt
letta_mcp_server-1.0.5.dist-info/RECORD
