Metadata-Version: 2.4
Name: letta-mcp-server
Version: 1.0.5
Summary: Production-ready MCP server bridging Claude and Letta.ai agents
Author-email: SNYCFIRE-CORE <Zack@ascendhq.gg>
Maintainer-email: SNYCFIRE-CORE <Zack@ascendhq.gg>
License-Expression: MIT
Project-URL: Homepage, https://github.com/SNYCFIRE-CORE/letta-mcp-server
Project-URL: Documentation, https://github.com/SNYCFIRE-CORE/letta-mcp-server/tree/main/docs
Project-URL: Repository, https://github.com/SNYCFIRE-CORE/letta-mcp-server
Project-URL: Issues, https://github.com/SNYCFIRE-CORE/letta-mcp-server/issues
Keywords: letta,mcp,claude,ai,agents,llm,model-context-protocol,fastmcp,memgpt
Classifier: Development Status :: 4 - Beta
Classifier: Intended Audience :: Developers
Classifier: Topic :: Software Development :: Libraries :: Python Modules
Classifier: Topic :: Scientific/Engineering :: Artificial Intelligence
Classifier: Programming Language :: Python :: 3
Classifier: Programming Language :: Python :: 3.10
Classifier: Programming Language :: Python :: 3.11
Classifier: Programming Language :: Python :: 3.12
Classifier: Operating System :: OS Independent
Classifier: Typing :: Typed
Requires-Python: >=3.10
License-File: LICENSE
Requires-Dist: fastmcp>=0.2.0
Requires-Dist: httpx>=0.27.0
Requires-Dist: pyyaml>=6.0
Requires-Dist: python-dotenv>=1.0.0
Requires-Dist: tenacity>=8.0.0
Requires-Dist: pydantic>=2.0.0
Provides-Extra: dev
Requires-Dist: pytest>=7.0.0; extra == "dev"
Requires-Dist: pytest-asyncio>=0.21.0; extra == "dev"
Requires-Dist: pytest-cov>=4.0.0; extra == "dev"
Requires-Dist: black>=23.0.0; extra == "dev"
Requires-Dist: flake8>=6.0.0; extra == "dev"
Requires-Dist: mypy>=1.0.0; extra == "dev"
Requires-Dist: pre-commit>=3.0.0; extra == "dev"
Requires-Dist: ruff>=0.1.0; extra == "dev"
Provides-Extra: docs
Requires-Dist: mkdocs>=1.5.0; extra == "docs"
Requires-Dist: mkdocs-material>=9.0.0; extra == "docs"
Requires-Dist: mkdocstrings[python]>=0.24.0; extra == "docs"
Dynamic: license-file
